MANIFEST.in
README.md
setup.py
django_simplesearch.egg-info/PKG-INFO
django_simplesearch.egg-info/SOURCES.txt
django_simplesearch.egg-info/dependency_links.txt
django_simplesearch.egg-info/top_level.txt
django_simplesearch.egg-info/zip-safe
simplesearch/__init__.py
simplesearch/constants.py
simplesearch/functions.py