Metadata-Version: 1.1
Name: django-simplesearch
Version: 1.0
Summary: A basic search application for Django.
Home-page: https://github.com/pigmonkey/django-simplesearch
Author: Julien Phalip, Peter Hogg
Author-email: peter@havenaut.net
License: UNKNOWN
Platform: UNKNOWN
Classifier: Programming Language :: Python
Classifier: Operating System :: OS Independent
Classifier: Development Status :: 5 - Production/Stable
Classifier: Framework :: Django
